Metadata-Version: 1.0
Name: powercontrol
Version: 0.1
Summary: Control power
Home-page: UNKNOWN
Author: takipsizad
Author-email: UNKNOWN
License: UNKNOWN
Platform: UNKNOWN
